Metadata-Version: 1.1
Name: New-Organic-Answers
Version: 0.0.1
Summary: A way to read Googles "Organic Answer Box"
Home-page: UNKNOWN
Author: Josh
Author-email: josher@gmail.com
License: MIT
Keywords: google scraper
Platform: UNKNOWN
Classifier: Development Status :: 5 - Production/Stable
Classifier: Intended Audience :: Education
Classifier: Operating System :: Microsoft :: Windows :: Windows 10
Classifier: License :: OSI Approved :: MIT License
Classifier: Programming Language :: Python :: 3
